Workbook

Sheet Regression
A1: SUMMARY OUTPUT
A3: Regression Statistics
A4: Multiple R | B4: 0.82672864
A5: R Square | B5: 0.68348025
A6: Adjusted R Square | B6: 0.67611933
A7: Standard Error | B7: 11824.611
A8: Observations | B8: 45
A10: ANOVA
B11: df | C11: SS | D11: MS | E11: F | F11: Significance F
A12: Regression | B12: 1 | C12: 1.2982769e+10 | D12: 1.2982769e+10 | E12: 92.852502 | F12: 2.6276688e-12
A13: Residual | B13: 43 | C13: 6.0123212e+09 | D13: 1.3982142e+08
A14: Total | B14: 44 | C14: 1.899509e+10
B16: Coefficients | C16: Standard Error | D16: t Stat | E16: P-value | F16: Lower 95% | G16: Upper 95% | H16: Lower 95.0% | I16: Upper 95.0%
A17: Intercept | B17: 42105.823 | C17: 3585.0066 | D17: 11.744978 | E17: 5.2600151e-15 | F17: 34875.968 | G17: 49335.678 | H17: 34875.968 | I17: 49335.678
A18: X Variable 1 | B18: 1307.8646 | C18: 135.72691 | D18: 9.6360003 | E18: 2.6276688e-12 | F18: 1034.1452 | G18: 1581.584 | H18: 1034.1452 | I18: 1581.584

Sheet Model
A1: n | B1: alpha | C1: gamma | D1: delta | E1: SSE | F1: MSE | G1: s
A2: =COUNT(C11:C56) -> 45 | B2: 0.86747152 | C2: 0.023390231 | D2: 0.044221855 | E2: =SUM(I11:I56) -> 1.2516195e+10 | F2: =E2/(A2-1) -> 2.8445898e+08 | G2: =SQRT(F2) -> 16865.912
G4: Forecast | I4: Squared
E5: Growth | F5: Sesonal | G5: Made Last | H5: Forecast | I5: Forecast
A6: Time | B6: remark | C6: y | D6: Level | E6: Rate | F6: Factor | G6: Period | H6: Error | I6: Error | L6: Time | M6: y | N6: y^ | O6: Monthly | S6: AVG | T6: SF
A7: -3 | F7: =R7*$T$7 -> 3.2161631 | L7: 1 | M7: =C11 -> 65000 | N7: =$D$10+$E$10*L7 -> 43413.687 | O7: =M7/N7 -> 1.4972237 | R7: =AVERAGE(O7,O11,O15,O19,O23,O27,O31,O35,O39,O43,O47,O51) -> 1.0742756 | S7: S[1] | T7: =12/SUM(R7:R10) -> 2.9937971
A8: -2 | F8: =R8*$T$7 -> 3.038154 | L8: 2 | M8: =C12 -> 53139 | N8: =$D$10+$E$10*L8 -> 44721.552 | O8: =M8/N8 -> 1.1882191 | R8: =AVERAGE(O8,O12,O16,O20,O24,O28,O32,O36,O40,O44,O48,O52) -> 1.0148163 | S8: S[2]
A9: -1 | F9: =R9*$T$7 -> 2.8424697 | L9: 3 | M9: =C13 -> 56222 | N9: =$D$10+$E$10*L9 -> 46029.416 | O9: =M9/N9 -> 1.2214363 | R9: =AVERAGE(O9,O13,O17,O21,O25,O29,O33,O37,O41,O45,O49,O53) -> 0.94945303 | S9: S[3]
A10: 0 | C10: Actual | D10: =$M$74 -> 42105.823 | E10: =$M$75 -> 1307.8646 | F10: =R10*$T$7 -> 2.9032131 | G10: Forecast | L10: 4 | M10: =C14 -> 48264 | N10: =$D$10+$E$10*L10 -> 47337.281 | O10: =M10/N10 -> 1.0195769 | R10: =AVERAGE(O10,O14,O18,O22,O26,O30,O34,O38,O42,O46,O50,O54) -> 0.96974279 | S10: S[4]
A11: 1 | B11: 2019-12 | C11: 65000 | D11: =$B$2*(C11/F7)+(1-$B$2)*(D10+E10) -> 23285.512 | E11: =$C$2*(D11-D10)+(1-$C$2)*E10 -> 837.06191 | F11: =$D$2*(C11/D11)+(1-$D$2)*F7 -> 3.1973808 | G11: =(D10+E10)*F7 -> 139625.5 | H11: =C11-G11 -> -74625.498 | I11: =H11^2 -> 5.5689649e+09 | L11: 5 | M11: =C15 -> 57200 | N11: =$D$10+$E$10*L11 -> 48645.146 | O11: =M11/N11 -> 1.1758624
A12: 2 | B12: 2020-01 | C12: 53139 | D12: =$B$2*(C12/F8)+(1-$B$2)*(D11+E11) -> 18369.486 | E12: =$C$2*(D12-D11)+(1-$C$2)*E11 -> 702.49586 | F12: =$D$2*(C12/D12)+(1-$D$2)*F8 -> 3.0317256 | G12: =(D11+E11)*F8 -> 73288.096 | H12: =C12-G12 -> -20149.096 | I12: =H12^2 -> 4.0598605e+08 | L12: 6 | M12: =C16 -> 49589 | N12: =$D$10+$E$10*L12 -> 49953.01 | O12: =M12/N12 -> 0.99271295
A13: 3 | B13: 2020-02 | C13: 56222 | D13: =$B$2*(C13/F9)+(1-$B$2)*(D12+E12) -> 19685.541 | E13: =$C$2*(D13-D12)+(1-$C$2)*E12 -> 716.84715 | F13: =$D$2*(C13/D13)+(1-$D$2)*F9 -> 2.8430683 | G13: =(D12+E12)*F9 -> 54211.532 | H13: =C13-G13 -> 2010.4676 | I13: =H13^2 -> 4041980.1 | L13: 7 | M13: =C17 -> 49589 | N13: =$D$10+$E$10*L13 -> 51260.875 | O13: =M13/N13 -> 0.96738497
A14: 4 | B14: 2020-03 | C14: 48264 | D14: =$B$2*(C14/F10)+(1-$B$2)*(D13+E13) -> 17125.038 | E14: =$C$2*(D14-D13)+(1-$C$2)*E13 -> 640.18917 | F14: =$D$2*(C14/D14)+(1-$D$2)*F10 -> 2.8994594 | G14: =(D13+E13)*F10 -> 59232.483 | H14: =C14-G14 -> -10968.483 | I14: =H14^2 -> 1.2030761e+08 | L14: 8 | M14: =C18 -> 60731.5 | N14: =$D$10+$E$10*L14 -> 52568.739 | O14: =M14/N14 -> 1.1552778
A15: 5 | B15: 2020-04 | C15: 57200 | D15: =$B$2*(C15/F11)+(1-$B$2)*(D14+E14) -> 17873.154 | E15: =$C$2*(D15-D14)+(1-$C$2)*E14 -> 642.7136 | F15: =$D$2*(C15/D15)+(1-$D$2)*F11 -> 3.1975113 | G15: =(D14+E14)*F11 -> 56802.197 | H15: =C15-G15 -> 397.80258 | I15: =H15^2 -> 158246.89 | L15: 9 | M15: =C19 -> 60731.5 | N15: =$D$10+$E$10*L15 -> 53876.604 | O15: =M15/N15 -> 1.1272333
A16: 6 | B16: 2020-05 | C16: 49589 | D16: =$B$2*(C16/F12)+(1-$B$2)*(D15+E15) -> 16642.844 | E16: =$C$2*(D16-D15)+(1-$C$2)*E15 -> 598.90313 | F16: =$D$2*(C16/D16)+(1-$D$2)*F12 -> 3.0294205 | G16: =(D15+E15)*F12 -> 56135.03 | H16: =C16-G16 -> -6546.0301 | I16: =H16^2 -> 42850510 | L16: 10 | M16: =C20 -> 55177.2 | N16: =$D$10+$E$10*L16 -> 55184.468 | O16: =M16/N16 -> 0.99986829
A17: 7 | B17: 2020-06 | C17: 49589 | D17: =$B$2*(C17/F13)+(1-$B$2)*(D16+E16) -> 17415.523 | E17: =$C$2*(D17-D16)+(1-$C$2)*E16 -> 602.96779 | F17: =$D$2*(C17/D17)+(1-$D$2)*F13 -> 2.84326 | G17: =(D16+E16)*F13 -> 49019.464 | H17: =C17-G17 -> 569.53633 | I17: =H17^2 -> 324371.63 | L17: 11 | M17: =C21 -> 39168 | N17: =$D$10+$E$10*L17 -> 56492.333 | O17: =M17/N17 -> 0.69333302
A18: 8 | B18: 2020-07 | C18: 60731.5 | D18: =$B$2*(C18/F14)+(1-$B$2)*(D17+E17) -> 20557.849 | E18: =$C$2*(D18-D17)+(1-$C$2)*E17 -> 662.36397 | F18: =$D$2*(C18/D18)+(1-$D$2)*F14 -> 2.9018791 | G18: =(D17+E17)*F14 -> 52243.882 | H18: =C18-G18 -> 8487.6179 | I18: =H18^2 -> 72039657 | L18: 12 | M18: =C22 -> 58366 | N18: =$D$10+$E$10*L18 -> 57800.198 | O18: =M18/N18 -> 1.0097889
A19: 9 | B19: 2020-08 | C19: 60731.5 | D19: =$B$2*(C19/F15)+(1-$B$2)*(D18+E18) -> 19288.486 | E19: =$C$2*(D19-D18)+(1-$C$2)*E18 -> 617.18044 | F19: =$D$2*(C19/D19)+(1-$D$2)*F15 -> 3.1953478 | G19: =(D18+E18)*F15 -> 67851.869 | H19: =C19-G19 -> -7120.3694 | I19: =H19^2 -> 50699660 | L19: 13 | M19: =C23 -> 59850 | N19: =$D$10+$E$10*L19 -> 59108.062 | O19: =M19/N19 -> 1.0125522
A20: 10 | B20: 2020-09 | C20: 55177.2 | D20: =$B$2*(C20/F16)+(1-$B$2)*(D19+E19) -> 18438.004 | E20: =$C$2*(D20-D19)+(1-$C$2)*E19 -> 582.85146 | F20: =$D$2*(C20/D20)+(1-$D$2)*F16 -> 3.0277913 | G20: =(D19+E19)*F16 -> 60302.634 | H20: =C20-G20 -> -5125.4341 | I20: =H20^2 -> 26270075 | L20: 14 | M20: =C24 -> 59850 | N20: =$D$10+$E$10*L20 -> 60415.927 | O20: =M20/N20 -> 0.99063282
A21: 11 | B21: 2020-10 | C21: 39168 | D21: =$B$2*(C21/F17)+(1-$B$2)*(D20+E20) -> 14470.864 | E21: =$C$2*(D21-D20)+(1-$C$2)*E20 -> 476.42612 | F21: =$D$2*(C21/D21)+(1-$D$2)*F17 -> 2.8372201 | G21: =(D20+E20)*F17 -> 54081.236 | H21: =C21-G21 -> -14913.236 | I21: =H21^2 -> 2.224046e+08 | L21: 15 | M21: =C25 -> 47668 | N21: =$D$10+$E$10*L21 -> 61723.791 | O21: =M21/N21 -> 0.7722792
A22: 12 | B22: 2020-11 | C22: 58366 | D22: =$B$2*(C22/F18)+(1-$B$2)*(D21+E21) -> 19428.548 | E22: =$C$2*(D22-D21)+(1-$C$2)*E21 -> 581.24376 | F22: =$D$2*(C22/D22)+(1-$D$2)*F18 -> 2.9064011 | G22: =(D21+E21)*F18 -> 43375.229 | H22: =C22-G22 -> 14990.771 | I22: =H22^2 -> 2.2472321e+08 | L22: 16 | M22: =C26 -> 33192 | N22: =$D$10+$E$10*L22 -> 63031.656 | O22: =M22/N22 -> 0.52659254
... A51: 41 | B51: 2023-04 | C51: 85000 | D51: =$B$2*(C51/F47)+(1-$B$2)*(D50+E50) -> 27634.388 | E51: =$C$2*(D51-D50)+(1-$C$2)*E50 -> 407.93801 | F51: =$D$2*(C51/D51)+(1-$D$2)*F47 -> 3.185798 | G51: =(D50+E50)*F47 -> 108980.68 | H51: =C51-G51 -> -23980.68 | I51: =H51^2 -> 5.75073e+08 | L51: 45 | M51: =C55 -> 131500 | N51: =$D$10+$E$10*L51 -> 100959.73 | O51: =M51/N51 -> 1.3024995
A52: 42 | B52: 2023-05 | C52: 90000 | D52: =$B$2*(C52/F48)+(1-$B$2)*(D51+E51) -> 29435.601 | E52: =$C$2*(D52-D51)+(1-$C$2)*E51 -> 440.52704 | F52: =$D$2*(C52/D52)+(1-$D$2)*F48 -> 3.0365416 | G52: =(D51+E51)*F48 -> 85124.468 | H52: =C52-G52 -> 4875.5316 | I52: =H52^2 -> 23770808
A53: 43 | B53: 2023-06 | C53: 90000 | D53: =$B$2*(C53/F49)+(1-$B$2)*(D52+E52) -> 31477.228 | E53: =$C$2*(D53-D52)+(1-$C$2)*E52 -> 477.97713 | F53: =$D$2*(C53/D53)+(1-$D$2)*F49 -> 2.8381373 | G53: =(D52+E52)*F49 -> 84763.425 | H53: =C53-G53 -> 5236.5753 | I53: =H53^2 -> 27421721
A54: 44 | B54: 2023-07 | C54: 95000 | D54: =$B$2*(C54/F50)+(1-$B$2)*(D53+E53) -> 32701.335 | E54: =$C$2*(D54-D53)+(1-$C$2)*E53 -> 495.42928 | F54: =$D$2*(C54/D54)+(1-$D$2)*F50 -> 2.8954351 | G54: =(D53+E53)*F50 -> 92509.962 | H54: =C54-G54 -> 2490.0382 | I54: =H54^2 -> 6200290.2
A55: 45 | B55: 2023-08 | C55: 131500 | D55: =$B$2*(C55/F51)+(1-$B$2)*(D54+E54) -> 40206.088 | E55: =$C$2*(D55-D54)+(1-$C$2)*E54 -> 659.37898 | F55: =$D$2*(C55/D55)+(1-$D$2)*F51 -> 3.1895503 | G55: =(D54+E54)*F51 -> 105758.19 | H55: =C55-G55 -> 25741.813 | I55: =H55^2 -> 6.6264094e+08
A56: 46 | B56: 2023-09 | G56: =($D$55+$E$55*J56)*F52 -> 124089.69 | J56: 1
A57: 47 | B57: 2023-10 | G57: =($D$55+$E$55*J57)*F53 -> 117853.21 | J57: 2
A58: 48 | B58: 2023-11 | G58: =($D$55+$E$55*J58)*F54 -> 122141.68 | J58: 3
A59: 49 | B59: 2023-12 | G59: =($D$55+$E$55*J59)*F55 -> 136651.83 | J59: 4
M73: Coefficients | N73: Standard Error | O73: t Stat | P73: P-value | Q73: Lower 95% | R73: Upper 95% | S73: Lower 95.0% | T73: Upper 95.0%
L74: Intercept | M74: =Regression!B17 -> 42105.823 | N74: =Regression!C17 -> 3585.0066 | O74: =Regression!D17 -> 11.744978 | P74: =Regression!E17 -> 5.2600151e-15 | Q74: =Regression!F17 -> 34875.968 | R74: =Regression!G17 -> 49335.678 | S74: =Regression!H17 -> 34875.968 | T74: =Regression!I17 -> 49335.678
L75: X Variable 1 | M75: =Regression!B18 -> 1307.8646 | N75: =Regression!C18 -> 135.72691 | O75: =Regression!D18 -> 9.6360003 | P75: =Regression!E18 -> 2.6276688e-12 | Q75: =Regression!F18 -> 1034.1452 | R75: =Regression!G18 -> 1581.584 | S75: =Regression!H18 -> 1034.1452 | T75: =Regression!I18 -> 1581.584

Sheet Trends

Sheet Monthly
B1: Actual | C1: Forecast | D1: Actual% | E1: Forecast%
A2: 2019-12 | B2: =Model!C11 -> 65000 | C2: =Model!G11 -> 139625.5
A3: 2020-01 | B3: =Model!C12 -> 53139 | C3: =Model!G12 -> 73288.096 | D3: =(B3-B2)/B2 -> -0.18247692 | E3: =(C3-C2)/C2 -> -0.47510951
A4: 2020-02 | B4: =Model!C13 -> 56222 | C4: =Model!G13 -> 54211.532 | D4: =(B4-B3)/B3 -> 0.058017652 | E4: =(C4-C3)/C3 -> -0.26029552
A5: 2020-03 | B5: =Model!C14 -> 48264 | C5: =Model!G14 -> 59232.483 | D5: =(B5-B4)/B4 -> -0.14154601 | E5: =(C5-C4)/C4 -> 0.092617751
A6: 2020-04 | B6: =Model!C15 -> 57200 | C6: =Model!G15 -> 56802.197 | D6: =(B6-B5)/B5 -> 0.18514835 | E6: =(C6-C5)/C5 -> -0.041029602
A7: 2020-05 | B7: =Model!C16 -> 49589 | C7: =Model!G16 -> 56135.03 | D7: =(B7-B6)/B6 -> -0.13305944 | E7: =(C7-C6)/C6 -> -0.011745449
A8: 2020-06 | B8: =Model!C17 -> 49589 | C8: =Model!G17 -> 49019.464 | D8: =(B8-B7)/B7 -> 0 | E8: =(C8-C7)/C7 -> -0.12675804
A9: 2020-07 | B9: =Model!C18 -> 60731.5 | C9: =Model!G18 -> 52243.882 | D9: =(B9-B8)/B8 -> 0.22469701 | E9: =(C9-C8)/C8 -> 0.06577833
A10: 2020-08 | B10: =Model!C19 -> 60731.5 | C10: =Model!G19 -> 67851.869 | D10: =(B10-B9)/B9 -> 0 | E10: =(C10-C9)/C9 -> 0.29875244
A11: 2020-09 | B11: =Model!C20 -> 55177.2 | C11: =Model!G20 -> 60302.634 | D11: =(B11-B10)/B10 -> -0.091456658 | E11: =(C11-C10)/C10 -> -0.11126054
A12: 2020-10 | B12: =Model!C21 -> 39168 | C12: =Model!G21 -> 54081.236 | D12: =(B12-B11)/B11 -> -0.29014158 | E12: =(C12-C11)/C11 -> -0.10316959
A13: 2020-11 | B13: =Model!C22 -> 58366 | C13: =Model!G22 -> 43375.229 | D13: =(B13-B12)/B12 -> 0.49014502 | E13: =(C13-C12)/C12 -> -0.19796158
A14: 2020-12 | B14: =Model!C23 -> 59850 | C14: =Model!G23 -> 63938.242 | D14: =(B14-B13)/B13 -> 0.025425762 | E14: =(C14-C13)/C13 -> 0.47407273
... A46: 2023-08 | B46: =Model!C55 -> 131500 | C46: =Model!G55 -> 105758.19 | D46: =(B46-B45)/B45 -> 0.38421053 | E46: =(C46-C45)/C45 -> 0.14320863
A47: 2023-09 | C47: =Model!G56 -> 124089.69 | E47: =(C47-C46)/C46 -> 0.17333412
A48: 2023-10 | C48: =Model!G57 -> 117853.21 | E48: =(C48-C47)/C47 -> -0.050257811
A49: 2023-11 | C49: =Model!G58 -> 122141.68 | E49: =(C49-C48)/C48 -> 0.036388243
A50: 2023-12 | C50: =Model!G59 -> 136651.83 | E50: =(C50-C49)/C49 -> 0.11879766

Sheet 20230630
A1: 结算管理周期： | B1: 44798 | C1: 至 | D1: 45107 | F1: =""&"实际收益率为"&ROUND(G6*100,1)&"%，小于2%，按照第一档位收取以下"&H2 -> 实际收益率为0.8%，小于2%，按照第一档位收取以下费用合计：8.22
A2: 管理本金： | B2: 2000 | F2: 本金管理费(本金*0.37%)： | G2: =B$2*0.0037 -> 7.4 | H2: ="费用合计："&ROUND(SUM(G2+G3),2) -> 费用合计：8.22
A3: 结算日期： | B3: 45107 | F3: 收益提成(收益*5%)： | G3: =IF(G5<=0,0,G5*0.05) -> 0.81593743
F4: 净收益： | G4: =G5-G2-G3 -> 8.1028112
A5: 账面收益： | B5: =SUM(D10:D43) -> 14.239622 | D5: 账面收益率： | F5: 实际收益： | G5: =SUM(G10:G43) -> 16.318749 | H5: 实际收益率：
A6: 账面收益/本金： | B6: =B5/B2 -> 0.0071198109 | D6: 月度 | E6: =B$5/(DATEDIF(B$1,B$3,"d")/30)/B$2 -> 0.00069124378 | F6: 实际收益/本金： | G6: =G5/B2 -> 0.0081593743 | H6: 月度 | I6: =G$5/(DATEDIF(B$1,B$3,"d")/30)/B$2 -> 0.00079217226
D7: 季度 | E7: =B$5/(DATEDIF(B$1,B$3,"d")/90)/B$2 -> 0.0020737313 | H7: 季度 | I7: =G$5/(DATEDIF(B$1,B$3,"d")/90)/B$2 -> 0.0023765168
D8: 年化 | E8: =B$5/(DATEDIF(B$1,B$3,"d")/365)/B$2 -> 0.0084101327 | H8: 年化 | I8: =G$5/(DATEDIF(B$1,B$3,"d")/365)/B$2 -> 0.0096380959
B9: 项目 | C9: 购买额 | D9: 账面收益/损失额 | E9: 账面收益率 | F9: 持有额 | G9: 实际收益/损失额 | H9: 实际收益率
B10: 华宝富时100A | C10: 26.666667 | D10: 4.85 | E10: =D10/C10 -> 0.181875 | F10: 1.09 | G10: =D10-F10 -> 3.76 | H10: =G10/C10 -> 0.141
B11: 广发纳指100ETF联接（QDII）C | C11: 86.666667 | D11: 11.6 | E11: =D11/C11 -> 0.13384615 | F11: 9.81 | G11: =D11-F11 -> 1.79 | H11: =G11/C11 -> 0.020653846
B12: 融通鑫新成长混合C | C12: 26.666667 | D12: 3.09 | E12: =D12/C12 -> 0.115875 | F12: 0.82 | G12: =D12-F12 -> 2.27 | H12: =G12/C12 -> 0.085125
B13: 大成360互联网+指数A | C13: 146.66667 | D13: 13.1 | E13: =D13/C13 -> 0.089318182 | F13: 9.22 | G13: =D13-F13 -> 3.88 | H13: =G13/C13 -> 0.026454545
B14: 广发中证基建工程ETF联接A | C14: 40 | D14: 3.19 | E14: =D14/C14 -> 0.07975 | F14: 0.05 | G14: =D14-F14 -> 3.14 | H14: =G14/C14 -> 0.0785
B15: 博时标普500ETF联接A | C15: 146.66667 | D15: 9.22 | E15: =D15/C15 -> 0.062863636 | F15: 9.07 | G15: =D15-F15 -> 0.15 | H15: =G15/C15 -> 0.0010227273
B16: 嘉实美国成长股票型证券 | C16: 126.66667 | D16: 5.73 | E16: =D16/C16 -> 0.045236842 | F16: 7.47 | G16: =D16-F16 -> -1.74 | H16: =G16/C16 -> -0.013736842
B17: 上投摩根日本精选股票(QDII) | C17: 53.333333 | D17: 1.89 | E17: =D17/C17 -> 0.0354375 | F17: 1.47 | G17: =D17-F17 -> 0.42 | H17: =G17/C17 -> 0.007875
B18: 博时创新经济混合C | C18: 26.666667 | D18: 0.86 | E18: =D18/C18 -> 0.03225 | F18: 0.86 | G18: =D18-F18 -> 0 | H18: =G18/C18 -> 0
B19: 嘉实全球互联网股票型证券 | C19: 80 | D19: 2.32 | E19: =D19/C19 -> 0.029 | F19: 0.96 | G19: =D19-F19 -> 1.36 | H19: =G19/C19 -> 0.017
B20: 欧元现汇 | C20: 60 | D20: 1.6596219 | E20: =D20/C20 -> 0.027660364 | F20: 1.4408732 | G20: =D20-F20 -> 0.21874862 | H20: =G20/C20 -> 0.0036458103
B21: 大成多策略混合(LOF)A | C21: 46.666667 | D21: 1.24 | E21: =D21/C21 -> 0.026571429 | F21: 0.79 | G21: =D21-F21 -> 0.45 | H21: =G21/C21 -> 0.0096428571
... B43: 国泰大农业股票A | C43: 26.666667 | D43: -8.5 | E43: =D43/C43 -> -0.31875 | F43: -7.98 | G43: =D43-F43 -> -0.52 | H43: =G43/C43 -> -0.0195

Sheet portrait
B2: 委托人自测画像 | D2: 姓名：
D3: 自测时间：
B5: 委托人按自身情况勾选或填色
B7: 1. | C7: 现金投资占比 | G7: 2. | H7: 投资风险敏感度
C8: 按自身年龄、家庭情况，分配用于投资的现金 | H8: 对投资亏损的承受度
C9: 20%持有—80%用于投资 | H9: <5%
C10: 30%持有—70%用于投资 | H10: <10%
C11: 50%持有—50%用于投资 | H11: <20%
H12: <30%
B15: 3. | C15: 投资时长 | G15: 4. | H15: 收益预期
C17: 少于3年 | H17: 跑赢大盘及通胀水平，年化收益期望在3%水平上下
C18: 3-5年 | H18: 年化收益期望在5%水平上下
C19: 超过5年 | H19: 愿意承担高风险以获取高收益，年化收益期望高于8%

Sheet inx
C1: price | D1: share | E1: % | F1: % | G1: % | H1: low | I1: mid | J1: high
A2: ‘#300 indx | H2: =SUM(H3:H4) -> -350 | I2: =SUM(I3:I4) -> -220 | J2: =SUM(J3:J4) -> -90
A3: 4 | B3: - | C3: -2 | D3: 500 | E3: 0.5 | F3: 0.4 | G3: 0.3 | H3: =$C3*$D3*E3 -> -500 | I3: =$C3*$D3*F3 -> -400 | J3: =$C3*$D3*G3 -> -300
A4: =A3*D3 -> 2000 | B4: + | C4: 0.6 | D4: 500 | E4: =1-E3 -> 0.5 | F4: =1-F3 -> 0.6 | G4: =1-G3 -> 0.7 | H4: =$C4*$D4*E4 -> 150 | I4: =$C4*$D4*F4 -> 180 | J4: =$C4*$D4*G4 -> 210
H5: =(H2/$A4) -> -0.175 | I5: =(I2/$A4) -> -0.11 | J5: =(J2/$A4) -> -0.045
A7: ‘#500 indx | H7: =SUM(H8:H9) -> -50 | I7: =SUM(I8:I9) -> 10 | J7: =SUM(J8:J9) -> 70
A8: 6.3 | B8: - | C8: -0.7 | D8: 500 | E8: 0.5 | F8: 0.4 | G8: 0.3 | H8: =$C8*$D8*E8 -> -175 | I8: =$C8*$D8*F8 -> -140 | J8: =$C8*$D8*G8 -> -105
A9: =A8*D8 -> 3150 | B9: + | C9: 0.5 | D9: 500 | E9: =1-E8 -> 0.5 | F9: =1-F8 -> 0.6 | G9: =1-G8 -> 0.7 | H9: =$C9*$D9*E9 -> 125 | I9: =$C9*$D9*F9 -> 150 | J9: =$C9*$D9*G9 -> 175
H10: =(H7/$A9) -> -0.015873016 | I10: =(I7/$A9) -> 0.0031746032 | J10: =(J7/$A9) -> 0.022222222
